Metadata-Version: 2.1
Name: jaxdl
Version: 0.0.3
Summary: JAX (Flax) Deep Learning Library
Home-page: https://github.com/patrickahrt/jaxdl
Author: Patrick Hart
License: MIT
Keywords: deep,machine,learning,reinforcement,research
Platform: UNKNOWN
Classifier: Development Status :: 3 - Alpha
Classifier: Intended Audience :: Developers
Classifier: Intended Audience :: Education
Classifier: Intended Audience :: Science/Research
Classifier: Programming Language :: Python :: 3
Classifier: Programming Language :: Python :: 3.6
Classifier: Programming Language :: Python :: 3.7
Classifier: Programming Language :: Python :: 3.8
Classifier: Programming Language :: Python :: 3.9
Classifier: Topic :: Scientific/Engineering :: Artificial Intelligence
License-File: LICENSE
